{"nodes": [{"id": "c_users_user_onedrive_desktop_projects_julie_ai_personal_assistant_julie_core_agent_handoff_py", "label": "agent_handoff.py", "file_type": "code", "source_file": "julie/core/agent_handoff.py", "source_location": "L1"}, {"id": "core_agent_handoff_handoff_to_agent", "label": "handoff_to_agent()", "file_type": "code", "source_file": "julie/core/agent_handoff.py", "source_location": "L6"}, {"id": "any", "label": "Any", "file_type": "code", "source_file": "julie/core/agent_handoff.py", "source_location": "L6"}, {"id": "core_agent_handoff_rationale_1", "label": "Agent handoff utilities for Julie.", "file_type": "rationale", "source_file": "julie/core/agent_handoff.py", "source_location": "L1"}], "edges": [{"source": "c_users_user_onedrive_desktop_projects_julie_ai_personal_assistant_julie_core_agent_handoff_py", "target": "typing", "relation": "imports_from", "context": "import", "confidence": "EXTRACTED", "source_file": "julie/core/agent_handoff.py", "source_location": "L3", "weight": 1.0}, {"source": "c_users_user_onedrive_desktop_projects_julie_ai_personal_assistant_julie_core_agent_handoff_py", "target": "core_agent_handoff_handoff_to_agent", "relation": "contains", "confidence": "EXTRACTED", "source_file": "julie/core/agent_handoff.py", "source_location": "L6", "weight": 1.0}, {"source": "core_agent_handoff_handoff_to_agent", "target": "any", "relation": "references", "context": "generic_arg", "confidence": "EXTRACTED", "source_file": "julie/core/agent_handoff.py", "source_location": "L6", "weight": 1.0}, {"source": "core_agent_handoff_rationale_1", "target": "c_users_user_onedrive_desktop_projects_julie_ai_personal_assistant_julie_core_agent_handoff_py", "relation": "rationale_for", "confidence": "EXTRACTED", "source_file": "julie/core/agent_handoff.py", "source_location": "L1", "weight": 1.0}], "raw_calls": []}